beeai_framework/__init__.py
beeai_framework/adapters/__init__.py
beeai_framework/adapters/amazon_bedrock/__init__.py
beeai_framework/adapters/amazon_bedrock/backend/README.md
beeai_framework/adapters/amazon_bedrock/backend/__init__.py
beeai_framework/adapters/amazon_bedrock/backend/chat.py
beeai_framework/adapters/anthropic/__init__.py
beeai_framework/adapters/anthropic/backend/__init__.py
beeai_framework/adapters/anthropic/backend/chat.py
beeai_framework/adapters/azure_openai/__init__.py
beeai_framework/adapters/azure_openai/backend/__init__.py
beeai_framework/adapters/azure_openai/backend/chat.py
beeai_framework/adapters/groq/__init__.py
beeai_framework/adapters/groq/backend/__init__.py
beeai_framework/adapters/groq/backend/chat.py
beeai_framework/adapters/langchain/__init__.py
beeai_framework/adapters/langchain/tools.py
beeai_framework/adapters/litellm/__init__.py
beeai_framework/adapters/litellm/chat.py
beeai_framework/adapters/litellm/utils.py
beeai_framework/adapters/ollama/__init__.py
beeai_framework/adapters/ollama/backend/__init__.py
beeai_framework/adapters/ollama/backend/chat.py
beeai_framework/adapters/openai/__init__.py
beeai_framework/adapters/openai/backend/__init__.py
beeai_framework/adapters/openai/backend/chat.py
beeai_framework/adapters/vertexai/__init__.py
beeai_framework/adapters/vertexai/backend/__init__.py
beeai_framework/adapters/vertexai/backend/chat.py
beeai_framework/adapters/watsonx/__init__.py
beeai_framework/adapters/watsonx/backend/__init__.py
beeai_framework/adapters/watsonx/backend/chat.py
beeai_framework/adapters/xai/__init__.py
beeai_framework/adapters/xai/backend/__init__.py
beeai_framework/adapters/xai/backend/chat.py
beeai_framework/agents/__init__.py
beeai_framework/agents/base.py
beeai_framework/agents/errors.py
beeai_framework/agents/experimental/remote/__init__.py
beeai_framework/agents/experimental/remote/agent.py
beeai_framework/agents/experimental/remote/events.py
beeai_framework/agents/experimental/remote/types.py
beeai_framework_patched_fr-0.1.21.dist-info/LICENSE
beeai_framework_patched_fr-0.1.21.dist-info/METADATA
beeai_framework_patched_fr-0.1.21.dist-info/WHEEL
beeai_framework_patched_fr-0.1.21.dist-info/entry_points.txt
beeai_framework_patched_fr-0.1.21.dist-info/RECORD
