Metadata-Version: 2.3
Name: beeai-framework-patched-fr
Version: 0.1.21
Summary: BeeAI Framework with bug fix for when retrieving datetime fields that don't have a dict attribute
License: Apache-2.0
Author: IBM Corp.
Maintainer: Alex Bozarth
Maintainer-email: ajbozart@us.ibm.com
Requires-Python: >=3.11,<4.0
Classifier: License :: OSI Approved :: Apache Software License
Classifier: Programming Language :: Python :: 3
Classifier: Programming Language :: Python :: 3.11
Classifier: Programming Language :: Python :: 3.12
Classifier: Programming Language :: Python :: 3.13
Provides-Extra: acp
Provides-Extra: duckduckgo
Provides-Extra: huggingface
Provides-Extra: langchain
Provides-Extra: mcp
Provides-Extra: search
Provides-Extra: wikipedia
Requires-Dist: acp-sdk (>=0.8.0,<0.9.0) ; extra == "acp"
Requires-Dist: aiofiles (>=24.1.0,<25.0.0)
Requires-Dist: cachetools (>=5.5.2,<6.0.0)
Requires-Dist: chevron (>=0.14.0,<0.15.0)
Requires-Dist: duckduckgo-search (>=8.0.0,<9.0.0) ; extra == "search" or extra == "duckduckgo"
Requires-Dist: json-repair (>=0.39.0,<0.40.0)
Requires-Dist: jsonref (>=1.1.0,<2.0.0)
Requires-Dist: langchain-community (>=0.3.19,<0.4.0) ; extra == "langchain"
Requires-Dist: langchain-core (>=0.3.41,<0.4.0) ; extra == "langchain"
Requires-Dist: langchain-ollama (>=0.3.1,<0.4.0) ; extra == "langchain"
Requires-Dist: langgraph (>=0.3.27,<0.4.0) ; extra == "langchain"
Requires-Dist: litellm (>=1.60.0,<2.0.0)
Requires-Dist: mcp (>=1.2.0,<2.0.0) ; extra == "mcp"
Requires-Dist: pydantic (>=2.10,<3.0)
Requires-Dist: pydantic-settings (>=2.9.0,<3.0.0)
Requires-Dist: requests (>=2.32,<3.0)
Requires-Dist: wikipedia-api (>=0.8.1,<0.9.0) ; extra == "search" or extra == "wikipedia"
Project-URL: Documentation, https://i-am-bee.github.io/beeai-framework/#/python/
Project-URL: Homepage, https://iambee.ai
Project-URL: Repository, https://github.com/i-am-bee/beeai-framework
